{"frames":{"biaotiti.png":{"frame":{"x":0,"y":0,"w":644,"h":102,"idx":0},"spriteSourceSize":{"x":0,"y":0},"sourceSize":{"w":644,"h":102}},"tie.png":{"frame":{"x":0,"y":104,"w":456,"h":100,"idx":0},"spriteSourceSize":{"x":0,"y":0},"sourceSize":{"w":456,"h":100}},"zaigong.png":{"frame":{"x":0,"y":206,"w":289,"h":42,"idx":0},"spriteSourceSize":{"x":0,"y":0},"sourceSize":{"w":290,"h":44}},"dianji.png":{"frame":{"x":291,"y":206,"w":154,"h":41,"idx":0},"spriteSourceSize":{"x":1,"y":0},"sourceSize":{"w":156,"h":41}}},"meta":{"app":"http:\/\/www.layabox.com","version":"1.00","format":"json","scale":1,"image":"mubiao.png","prefix":"comp\/mubiao\/","md5":"2aa069627f54cb55f454887f20083c1d"}}
