{
  "file": "tongyong2.png",
  "frames": {
    "wenhao": {
      "x": 659,
      "y": 173,
      "w": 42,
      "h": 42,
      "offX": 0,
      "offY": 0,
      "sourceW": 42,
      "sourceH": 42
    },
    "bosswzbg": {
      "x": 450,
      "y": 102,
      "w": 167,
      "h": 30,
      "offX": 1,
      "offY": 0,
      "sourceW": 169,
      "sourceH": 30
    },
    "star3": {
      "x": 703,
      "y": 180,
      "w": 17,
      "h": 17,
      "offX": 0,
      "offY": 0,
      "sourceW": 17,
      "sourceH": 17
    },
    "btn81": {
      "x": 596,
      "y": 1,
      "w": 102,
      "h": 46,
      "offX": 3,
      "offY": 0,
      "sourceW": 108,
      "sourceH": 46
    },
    "szheji1": {
      "x": 783,
      "y": 136,
      "w": 21,
      "h": 25,
      "offX": 0,
      "offY": 0,
      "sourceW": 21,
      "sourceH": 25
    },
    "line_black": {
      "x": 103,
      "y": 215,
      "w": 10,
      "h": 3,
      "offX": 0,
      "offY": 0,
      "sourceW": 10,
      "sourceH": 3
    },
    "paihang3": {
      "x": 136,
      "y": 317,
      "w": 48,
      "h": 49,
      "offX": 0,
      "offY": 0,
      "sourceW": 49,
      "sourceH": 50
    },
    "szzhanwen2": {
      "x": 549,
      "y": 259,
      "w": 30,
      "h": 29,
      "offX": 0,
      "offY": 0,
      "sourceW": 30,
      "sourceH": 29
    },
    "btnadd": {
      "x": 252,
      "y": 248,
      "w": 50,
      "h": 50,
      "offX": 0,
      "offY": 0,
      "sourceW": 50,
      "sourceH": 50
    },
    "touxiangkuang0": {
      "x": 485,
      "y": 242,
      "w": 30,
      "h": 30,
      "offX": 0,
      "offY": 0,
      "sourceW": 30,
      "sourceH": 30
    },
    "tjweijihuo": {
      "x": 92,
      "y": 259,
      "w": 56,
      "h": 56,
      "offX": 0,
      "offY": 0,
      "sourceW": 56,
      "sourceH": 56
    },
    "szbanggong": {
      "x": 450,
      "y": 73,
      "w": 26,
      "h": 26,
      "offX": 0,
      "offY": 0,
      "sourceW": 26,
      "sourceH": 26
    },
    "quality5": {
      "x": 834,
      "y": 1,
      "w": 64,
      "h": 64,
      "offX": 0,
      "offY": 0,
      "sourceW": 64,
      "sourceH": 64
    },
    "paihang2": {
      "x": 516,
      "y": 176,
      "w": 47,
      "h": 49,
      "offX": 1,
      "offY": 0,
      "sourceW": 49,
      "sourceH": 50
    },
    "weijihuo2": {
      "x": 365,
      "y": 193,
      "w": 80,
      "h": 32,
      "offX": 0,
      "offY": 0,
      "sourceW": 80,
      "sourceH": 32
    },
    "tongyongadd2": {
      "x": 85,
      "y": 317,
      "w": 49,
      "h": 49,
      "offX": 0,
      "offY": 0,
      "sourceW": 50,
      "sourceH": 49
    },
    "quality0": {
      "x": 809,
      "y": 67,
      "w": 64,
      "h": 64,
      "offX": 0,
      "offY": 0,
      "sourceW": 64,
      "sourceH": 64
    },
    "zhandouli2": {
      "x": 703,
      "y": 199,
      "w": 38,
      "h": 42,
      "offX": 2,
      "offY": 2,
      "sourceW": 41,
      "sourceH": 44
    },
    "tjyijihuo": {
      "x": 34,
      "y": 259,
      "w": 56,
      "h": 56,
      "offX": 0,
      "offY": 0,
      "sourceW": 56,
      "sourceH": 56
    },
    "btnmax": {
      "x": 150,
      "y": 262,
      "w": 50,
      "h": 50,
      "offX": 0,
      "offY": 0,
      "sourceW": 50,
      "sourceH": 50
    },
    "tongyongdian2": {
      "x": 722,
      "y": 180,
      "w": 15,
      "h": 15,
      "offX": 0,
      "offY": 0,
      "sourceW": 15,
      "sourceH": 15
    },
    "yeqian4": {
      "x": 325,
      "y": 133,
      "w": 123,
      "h": 58,
      "offX": 18,
      "offY": 0,
      "sourceW": 141,
      "sourceH": 58
    },
    "paihangs3": {
      "x": 682,
      "y": 136,
      "w": 19,
      "h": 19,
      "offX": 1,
      "offY": 2,
      "sourceW": 21,
      "sourceH": 21
    },
    "wupingkuangNB": {
      "x": 495,
      "y": 1,
      "w": 99,
      "h": 99,
      "offX": 0,
      "offY": 0,
      "sourceW": 100,
      "sourceH": 100
    },
    "line_light": {
      "x": 186,
      "y": 314,
      "w": 10,
      "h": 3,
      "offX": 0,
      "offY": 0,
      "sourceW": 10,
      "sourceH": 3
    },
    "btn62": {
      "x": 189,
      "y": 145,
      "w": 102,
      "h": 46,
      "offX": 0,
      "offY": 0,
      "sourceW": 102,
      "sourceH": 46
    },
    "jiantouxuan": {
      "x": 703,
      "y": 136,
      "w": 37,
      "h": 42,
      "offX": 1,
      "offY": 0,
      "sourceW": 39,
      "sourceH": 42
    },
    "tongyongbg_dark": {
      "x": 103,
      "y": 203,
      "w": 10,
      "h": 10,
      "offX": 0,
      "offY": 0,
      "sourceW": 10,
      "sourceH": 10
    },
    "btn-": {
      "x": 304,
      "y": 248,
      "w": 50,
      "h": 50,
      "offX": 0,
      "offY": 0,
      "sourceW": 50,
      "sourceH": 50
    },
    "szexp": {
      "x": 425,
      "y": 278,
      "w": 23,
      "h": 22,
      "offX": 6,
      "offY": 0,
      "sourceW": 34,
      "sourceH": 22
    },
    "tongyongzuobiao": {
      "x": 549,
      "y": 227,
      "w": 29,
      "h": 30,
      "offX": 0,
      "offY": 0,
      "sourceW": 29,
      "sourceH": 30
    },
    "tongyongbg_light": {
      "x": 682,
      "y": 157,
      "w": 10,
      "h": 10,
      "offX": 0,
      "offY": 0,
      "sourceW": 10,
      "sourceH": 10
    },
    "jiantouyou": {
      "x": 202,
      "y": 262,
      "w": 41,
      "h": 60,
      "offX": 0,
      "offY": 1,
      "sourceW": 41,
      "sourceH": 62
    },
    "paihang1": {
      "x": 34,
      "y": 317,
      "w": 49,
      "h": 50,
      "offX": 0,
      "offY": 0,
      "sourceW": 49,
      "sourceH": 50
    },
    "szzhanwen": {
      "x": 580,
      "y": 225,
      "w": 26,
      "h": 29,
      "offX": 0,
      "offY": 0,
      "sourceW": 26,
      "sourceH": 29
    },
    "guwu": {
      "x": 700,
      "y": 1,
      "w": 66,
      "h": 67,
      "offX": 2,
      "offY": 3,
      "sourceW": 70,
      "sourceH": 70
    },
    "chatfind": {
      "x": 1,
      "y": 259,
      "w": 31,
      "h": 112,
      "offX": 0,
      "offY": 0,
      "sourceW": 31,
      "sourceH": 112
    },
    "btn60": {
      "x": 596,
      "y": 49,
      "w": 102,
      "h": 46,
      "offX": 0,
      "offY": 0,
      "sourceW": 102,
      "sourceH": 46
    },
    "manji": {
      "x": 189,
      "y": 199,
      "w": 61,
      "h": 61,
      "offX": 4,
      "offY": 5,
      "sourceW": 70,
      "sourceH": 70
    },
    "kejihuo": {
      "x": 365,
      "y": 227,
      "w": 80,
      "h": 32,
      "offX": 0,
      "offY": 0,
      "sourceW": 80,
      "sourceH": 32
    },
    "duoxuangou": {
      "x": 742,
      "y": 136,
      "w": 39,
      "h": 38,
      "offX": 0,
      "offY": 0,
      "sourceW": 39,
      "sourceH": 38
    },
    "quality4": {
      "x": 743,
      "y": 70,
      "w": 64,
      "h": 64,
      "offX": 0,
      "offY": 0,
      "sourceW": 64,
      "sourceH": 64
    },
    "jingyantiao1": {
      "x": 619,
      "y": 97,
      "w": 122,
      "h": 37,
      "offX": 0,
      "offY": 0,
      "sourceW": 122,
      "sourceH": 37
    },
    "btn70": {
      "x": 1,
      "y": 93,
      "w": 160,
      "h": 50,
      "offX": 0,
      "offY": 0,
      "sourceW": 160,
      "sourceH": 50
    },
    "btnshousuo": {
      "x": 565,
      "y": 176,
      "w": 47,
      "h": 47,
      "offX": 0,
      "offY": 0,
      "sourceW": 47,
      "sourceH": 47
    },
    "paihangs1": {
      "x": 245,
      "y": 300,
      "w": 21,
      "h": 21,
      "offX": 0,
      "offY": 0,
      "sourceW": 21,
      "sourceH": 21
    },
    "btn80": {
      "x": 450,
      "y": 134,
      "w": 106,
      "h": 40,
      "offX": 0,
      "offY": 0,
      "sourceW": 106,
      "sourceH": 40
    },
    "touxiangkuang1": {
      "x": 393,
      "y": 261,
      "w": 30,
      "h": 30,
      "offX": 0,
      "offY": 0,
      "sourceW": 30,
      "sourceH": 30
    },
    "bantoumingkuang3": {
      "x": 1,
      "y": 1,
      "w": 278,
      "h": 90,
      "offX": 0,
      "offY": 0,
      "sourceW": 278,
      "sourceH": 90
    },
    "zjmhongdian2": {
      "x": 245,
      "y": 323,
      "w": 20,
      "h": 22,
      "offX": 0,
      "offY": 0,
      "sourceW": 20,
      "sourceH": 22
    },
    "touxiangkuang3": {
      "x": 252,
      "y": 193,
      "w": 58,
      "h": 50,
      "offX": 0,
      "offY": 0,
      "sourceW": 58,
      "sourceH": 50
    },
    "quality1": {
      "x": 809,
      "y": 133,
      "w": 64,
      "h": 64,
      "offX": 0,
      "offY": 0,
      "sourceW": 64,
      "sourceH": 64
    },
    "fanhui": {
      "x": 116,
      "y": 145,
      "w": 71,
      "h": 74,
      "offX": 0,
      "offY": 1,
      "sourceW": 71,
      "sourceH": 75
    },
    "tongyongdian": {
      "x": 425,
      "y": 261,
      "w": 15,
      "h": 15,
      "offX": 0,
      "offY": 0,
      "sourceW": 15,
      "sourceH": 15
    },
    "paihangs2": {
      "x": 186,
      "y": 324,
      "w": 21,
      "h": 20,
      "offX": 0,
      "offY": 1,
      "sourceW": 21,
      "sourceH": 21
    },
    "bantoumingkuang4": {
      "x": 281,
      "y": 1,
      "w": 212,
      "h": 70,
      "offX": 0,
      "offY": 0,
      "sourceW": 212,
      "sourceH": 70
    },
    "star2": {
      "x": 447,
      "y": 242,
      "w": 36,
      "h": 34,
      "offX": 0,
      "offY": 0,
      "sourceW": 36,
      "sourceH": 34
    },
    "tongyongline3": {
      "x": 186,
      "y": 346,
      "w": 1,
      "h": 74,
      "offX": 0,
      "offY": 0,
      "sourceW": 1,
      "sourceH": 74
    },
    "quality2": {
      "x": 768,
      "y": 1,
      "w": 64,
      "h": 64,
      "offX": 0,
      "offY": 0,
      "sourceW": 64,
      "sourceH": 64
    },
    "btn72": {
      "x": 163,
      "y": 93,
      "w": 160,
      "h": 50,
      "offX": 0,
      "offY": 0,
      "sourceW": 160,
      "sourceH": 50
    },
    "star1": {
      "x": 356,
      "y": 261,
      "w": 35,
      "h": 34,
      "offX": 0,
      "offY": 0,
      "sourceW": 36,
      "sourceH": 34
    },
    "tongyongadd": {
      "x": 312,
      "y": 193,
      "w": 51,
      "h": 53,
      "offX": 0,
      "offY": 0,
      "sourceW": 51,
      "sourceH": 53
    },
    "tuijian2": {
      "x": 558,
      "y": 136,
      "w": 62,
      "h": 35,
      "offX": 0,
      "offY": 0,
      "sourceW": 63,
      "sourceH": 36
    },
    "szjingmai": {
      "x": 517,
      "y": 242,
      "w": 30,
      "h": 30,
      "offX": 0,
      "offY": 0,
      "sourceW": 30,
      "sourceH": 30
    },
    "scitembg": {
      "x": 1,
      "y": 145,
      "w": 113,
      "h": 56,
      "offX": 0,
      "offY": 0,
      "sourceW": 113,
      "sourceH": 56
    },
    "yilingqu": {
      "x": 103,
      "y": 221,
      "w": 80,
      "h": 32,
      "offX": 0,
      "offY": 0,
      "sourceW": 80,
      "sourceH": 32
    },
    "bossbgkuang": {
      "x": 1,
      "y": 203,
      "w": 100,
      "h": 54,
      "offX": 0,
      "offY": 0,
      "sourceW": 100,
      "sourceH": 54
    },
    "szkey": {
      "x": 293,
      "y": 145,
      "w": 30,
      "h": 30,
      "offX": 0,
      "offY": 0,
      "sourceW": 30,
      "sourceH": 30
    },
    "quality3": {
      "x": 450,
      "y": 176,
      "w": 64,
      "h": 64,
      "offX": 0,
      "offY": 0,
      "sourceW": 64,
      "sourceH": 64
    },
    "yeqian5": {
      "x": 325,
      "y": 73,
      "w": 123,
      "h": 58,
      "offX": 18,
      "offY": 0,
      "sourceW": 141,
      "sourceH": 58
    },
    "tuijian": {
      "x": 700,
      "y": 70,
      "w": 36,
      "h": 21,
      "offX": 0,
      "offY": 0,
      "sourceW": 36,
      "sourceH": 21
    },
    "duoxuankuang": {
      "x": 614,
      "y": 173,
      "w": 43,
      "h": 43,
      "offX": 0,
      "offY": 0,
      "sourceW": 43,
      "sourceH": 43
    },
    "jingyantiao4": {
      "x": 742,
      "y": 176,
      "w": 59,
      "h": 21,
      "offX": 0,
      "offY": 0,
      "sourceW": 59,
      "sourceH": 21
    },
    "jingyantiao6": {
      "x": 622,
      "y": 136,
      "w": 58,
      "h": 25,
      "offX": 0,
      "offY": 0,
      "sourceW": 58,
      "sourceH": 25
    }
  }
}